condition_chain/__init__.py
condition_chain/__version__.py
condition_chain/core.py
condition_chain-1.0.0.dist-info/DESCRIPTION.rst
condition_chain-1.0.0.dist-info/METADATA
condition_chain-1.0.0.dist-info/RECORD
condition_chain-1.0.0.dist-info/WHEEL
condition_chain-1.0.0.dist-info/metadata.json
condition_chain-1.0.0.dist-info/top_level.txt
